Workbook

Sheet 项目概况
B2: 临汾路街道业委会智能履职辅助项目 · 申报测算表
B4: 项目名称 | C4: 临汾路街道业委会智能履职辅助项目
B5: 申报单位 | C5: 上海市静安区人民政府临汾路街道办事处
B6: 建设性质 | C6: 新建（自主从零开发）
B7: 建设内容 | C7: 会议全链路、AI录音转写与纪要、业主接待、学习培训、印章登记、履职档案与可信存证
B8: 交付形态 | C8: 微信小程序 + 管理后台 + AI语音/大模型服务；对接街道现有可信档案馆存证
B9: 算力资源 | C9: 大模型、语音识别等算力资源由政府侧统一承担，不计入本项目预算
B11: 申 报 汇 总
B12: 预计人月合计 | D12: ='成本测算与申报预算'!C19 | E12: 人月
B13: 人月单价 | D13: ='成本测算与申报预算'!D3 | E13: 万元/人月
B14: 软件开发费（申报） | D14: ='成本测算与申报预算'!F19 | E14: 万元
B15: 其他费用（申报） | D15: ='成本测算与申报预算'!F31 | E15: 万元
B16: 建设周期 | D16: =建设周期!D7 | E16: 个月
B17: 项目预计总成本 | D17: ='成本测算与申报预算'!E33
B18: 财政申报金额 | D18: ='成本测算与申报预算'!F33
B19: 差额（前期自筹/自有经费） | D19: ='成本测算与申报预算'!E33-'成本测算与申报预算'!F33
B21: 说明：预计总成本为据实测算的项目价值；财政申报金额压缩至 40 万元，差额部分由前期自筹投入/街道自有经费承担。明细见「成本测算与申报预算」表，数字随蓝色单元格实时联动。

Sheet 功能模块清单
A1: 功能模块清单（申报建设内容）
A2: 序号 | B2: 一级功能模块 | C2: 二级功能 | D2: 功能说明 | E2: 当前状态
A3: 1 | B3: 业委会会议智能辅助 | C3: 会议全链路 | D3: 会议创建、议题与材料、居委会列席、线下签到与表决签字表、线上会议主任程序把关、表决结果登记 | E3: 已开发原型
A4: 2 | B4: 业委会会议智能辅助 | C4: 纪要公示状态机 | D4: 公示/撤回留痕、公示后不可静默改、纪要修订版本历史、对外脱敏与撤回墓碑态 | E4: 已开发原型
A5: 3 | B5: AI会议助手 | C5: 录音转写与纪要 | D5: 语音识别转写、议题整理、纪要初稿自动生成、待办提取 | E5: 已开发原型
A6: 4 | B6: 通知送达与时限提醒 | C6: 通知与期限 | D6: 提前7天通知、送达记录、会后3日公示提醒、年度会议次数统计 | E6: 已开发原型
A7: 5 | B7: 业主接待与反馈闭环 | C7: 接待与反馈 | D7: 接待登记、物业反馈留痕、业主反馈结果、年度接待统计 | E7: 已开发原型
A8: 6 | B8: 政策学习与业务培训 | C8: 学习培训 | D8: 学习/培训记录、参训人员、签到与材料、年度统计、政策资料智能检索问答 | E8: 已开发原型
A9: 7 | B9: 印章使用登记与风险留痕 | C9: 用印台账 | D9: 印章与保管委员、用印记录与确认、签字盖章件上传、台账查询导出 | E9: 本期新增开发
A10: 8 | B10: 履职档案与可信存证 | C10: 归档与存证 | D10: 材料分类归档、年度履职电子档案、公示纪要对接可信档案馆存证与一键验真 | E10: 已开发原型
A11: 9 | B11: 公开信息与业主端 | C11: 对外公开 | D11: 已公示纪要/结果对业主公开、公开音频、结果分享、物业公开信息 | E11: 已开发原型
A12: 10 | B12: 权限、安全与敏感信息保护 | C12: 角色权限 | D12: 6类角色权限矩阵、阶段锁定、敏感信息脱敏、操作留痕 | E12: 已开发原型
A13: 11 | B13: 企业微信/身份认证集成 | C13: 登录与组织 | D13: 身份认证登录、企业微信/组织对接 | E13: 已开发原型
A14: 12 | B14: 履职数据统计与仪表盘 | C14: 数据看板 | D14: 履职看板、送达率/签到率/参与率等年度统计 | E14: 已开发原型
A15: 13 | B15: 附件与文件服务 | C15: 文件管理 | D15: 附件上传、存储、导出等基础文件服务 | E15: 已开发原型
A16: 注：「已开发原型」指前期已自主完成核心功能原型开发与验证（现有代码：后端13个服务模块约1.5万行、小程序22个页面约2.3万行、语音服务约0.2万行）；本次申报为正式立项建设，含功能完善、印章模块新增、可信档案馆对接、测试验收与一年运维。

Sheet 成本测算与申报预算
A1: 成本测算与申报预算明细
B3: 开发人月综合单价（可调，蓝色） | D3: 2 | E3: 单位：万元 / 人月；上海中端市场价 2.0，可在 1.8～2.5 调整
A5: 一、应用软件开发费
A6: 序号 | B6: 功能模块 | C6: 人月 | D6: 单价 | E6: 预计成本(万元) | F6: 申报预算(万元) | G6: 说明
A7: 1 | B7: 业委会会议智能辅助（含公示状态机/纪要修订） | C7: 5 | D7: =$D$3 | E7: =C7*$D$3 | F7: 6 | G7: 已开发原型，本期完善
A8: 2 | B8: AI会议助手（录音转写+纪要生成） | C8: 3.5 | D8: =$D$3 | E8: =C8*$D$3 | F8: 4 | G8: 已开发原型，本期完善
A9: 3 | B9: 通知送达与时限提醒 | C9: 1.5 | D9: =$D$3 | E9: =C9*$D$3 | F9: 2 | G9: 已开发原型
A10: 4 | B10: 业主接待与反馈闭环 | C10: 2 | D10: =$D$3 | E10: =C10*$D$3 | F10: 3 | G10: 已开发原型，本期完善
A11: 5 | B11: 政策学习与业务培训 | C11: 1.5 | D11: =$D$3 | E11: =C11*$D$3 | F11: 2 | G11: 已开发原型
A12: 6 | B12: 印章使用登记与风险留痕 | C12: 1.5 | D12: =$D$3 | E12: =C12*$D$3 | F12: 3 | G12: 本期新增开发，全额申报
A13: 7 | B13: 履职档案与可信存证（含档案馆接口） | C13: 2.5 | D13: =$D$3 | E13: =C13*$D$3 | F13: 4 | G13: 存证对接为本期重点
A14: 8 | B14: 公开信息与业主端 | C14: 1.5 | D14: =$D$3 | E14: =C14*$D$3 | F14: 2 | G14: 已开发原型
A15: 9 | B15: 权限、安全与敏感信息保护 | C15: 2 | D15: =$D$3 | E15: =C15*$D$3 | F15: 3 | G15: 已开发原型，本期完善
A16: 10 | B16: 企业微信/身份认证集成 | C16: 1 | D16: =$D$3 | E16: =C16*$D$3 | F16: 1 | G16: 已开发原型
A17: 11 | B17: 履职数据统计与仪表盘 | C17: 1 | D17: =$D$3 | E17: =C17*$D$3 | F17: 1 | G17: 已开发原型
A18: 12 | B18: 附件与文件服务 | C18: 1 | D18: =$D$3 | E18: =C18*$D$3 | F18: 1 | G18: 已开发原型
A19: 应用软件开发 小计 | C19: =SUM(C7:C18) | E19: =SUM(E7:E18) | F19: =SUM(F7:F18)
A21: 二、其他费用
A22: 序号 | B22: 费用科目 | E22: 预计成本(万元) | F22: 申报预算(万元) | G22: 说明
A23: 1 | B23: 系统部署与环境初始化 | E23: 1.5 | F23: 1 | G23: 服务器环境、部署上线
A24: 2 | B24: 基础数据初始化与迁移 | E24: 0.5 | F24: 0.5 | G24: 业委会/小区/角色等基础数据
A25: 3 | B25: 软件测试与第三方验收支持 | E25: 2 | F25: 2 | G25: 功能/性能测试、验收配合
A26: 4 | B26: 用户培训（辖区推广） | E26: 0.7 | F26: 0.7 | G26: 各业委会现场培训
A27: 5 | B27: 操作手册与文档 | E27: 0.3 | F27: 0.3 | G27: 用户手册、运维文档
A28: 6 | B28: 一年运行维护服务 | E28: 3.5 | F28: 3 | G28: 上线后一年维保
A29: 7 | B29: 安全配置与等保符合 | E29: 0.3 | F29: 0.3 | G29: 安全加固、合规配置
A30: 8 | B30: 数据备份与容灾 | E30: 0.2 | F30: 0.2 | G30: 定期备份、容灾
A31: 其他费用 小计 | E31: =SUM(E23:E30) | F31: =SUM(F23:F30)
A33: 合 计 | E33: =E19+E31 | F33: =F19+F31
A35: 项目预计总成本 | E35: =E33
A36: 财政申报金额（本次立项申请） | E36: =F33
A37: 差额：前期已自筹投入 / 街道自有经费承担 | E37: =E33-F33
A39: · 计价口径：项目为自主从零开发，预计总成本按 人月×单价 据实测算；财政申报金额压缩至 40 万元。
A40: · 成本与申报差额部分，系前期已自筹完成核心功能原型开发的投入，不纳入本次财政重复申报。
A41: · 大模型/语音识别等算力资源由政府侧统一承担，不计入本预算。
A42: · 蓝色单元格为可调输入：各模块人月(C列)、人月单价(D3)、各项申报预算(F列)、其他费用成本/申报(E/F列)。
A43: · 如需进一步压降申报金额，可下调 F 列各项申报预算后自动重算。

Sheet 建设周期
A1: 建设周期（预计）
A2: 序号 | B2: 阶段 | C2: 主要内容 | D2: 时长(月)
A3: 1 | B3: 项目准备 | C3: 需求确认、建设内容细化、资金落实与采购准备 | D3: 0.5
A4: 2 | B4: 设计开发 | C4: 系统设计、功能完善、印章模块新增、AI能力接入、可信档案馆接口开发 | D4: 3
A5: 3 | B5: 部署试用 | C5: 系统部署、基础资料初始化、用户培训、辖区推广试用与优化 | D5: 2
A6: 4 | B6: 验收 | C6: 软件测试、材料整理、问题整改与项目验收 | D6: 1
A7: 合计建设周期 | D7: =SUM(D3:D6)
